{
  "Changes": [
    {
      "Action": "EditData",
      "Target": "Data/Weapons",
      "Entries": {
        "StonedValley.HeavyBong": {
          "Name": "StonedValley.HeavyBong",
          "DisplayName": "{{i18n: StonedValley.HeavyBong.name }}",
          "Description": "{{i18n: StonedValley.HeavyBong.description }}",
          "Type": 2,
          "MinDamage": 40,
          "MaxDamage": 55,
          "Knockback": 0.3,
          "Speed": 2,
          "Precision": 0,
          "Defense": 1,
          "CritChance": 0.02,
          "CritMultiplier": 3.0,
          "Texture": "DookieMaster.StonedValley/Weapons",
          "SpriteIndex": 0
        },
        "StonedValley.SherlockDagger": {
          "Name": "StonedValley.SherlockDagger",
          "DisplayName": "{{i18n: StonedValley.SherlockDagger.name }}",
          "Description": "{{i18n: StonedValley.SherlockDagger.description }}",
          "Type": 1,
          "MinDamage": 20,
          "MaxDamage": 35,
          "Knockback": 0.2,
          "Speed": 4,
          "Precision": 0,
          "Defense": 0,
          "CritChance": 0.10,
          "CritMultiplier": 3.2,
          "Texture": "DookieMaster.StonedValley/Weapons",
          "SpriteIndex": 1
        },
        "StonedValley.DabPick": {
          "Name": "StonedValley.DabPick",
          "DisplayName": "{{i18n: StonedValley.DabPick.name }}",
          "Description": "{{i18n: StonedValley.DabPick.description }}",
          "Type": 0,
          "MinDamage": 30,
          "MaxDamage": 45,
          "Knockback": 0.25,
          "Speed": 1,
          "Precision": 0,
          "Defense": 0,
          "CritChance": 0.05,
          "CritMultiplier": 3.0,
          "Texture": "DookieMaster.StonedValley/Weapons",
          "SpriteIndex": 2
        }
      }
    }
  ]
}
